skydive/entry.py
skydive-0.0.1.dist-info/LICENSE
skydive-0.0.1.dist-info/METADATA
skydive-0.0.1.dist-info/WHEEL
skydive-0.0.1.dist-info/entry_points.txt
skydive-0.0.1.dist-info/top_level.txt
skydive-0.0.1.dist-info/RECORD
