Metadata-Version: 2.1
Name: skydive
Version: 0.0.1
Summary: Tool for attacking Hybrid Active Directory
Home-page: https://github.com/ly4k/Skydive
Author: ly4k
License: MIT
License-File: LICENSE
